mcp_knowledge_base/__init__.py
mcp_knowledge_base/obsidian.py
mcp_knowledge_base/server.py
mcp_knowledge_base/tools.py
mcp_knowledge_base-0.1.0.dist-info/METADATA
mcp_knowledge_base-0.1.0.dist-info/WHEEL
mcp_knowledge_base-0.1.0.dist-info/entry_points.txt
mcp_knowledge_base-0.1.0.dist-info/RECORD
