Metadata-Version: 2.3
Name: mcp-knowledge-base
Version: 0.1.0
Summary: Example MCP server to create a knowledge-base
Author-email: Markus Pfundstein <markus@life-electronic.nl>
Requires-Python: >=3.13
Requires-Dist: mcp>=1.0.0
Requires-Dist: python-dotenv>=1.0.1
Requires-Dist: requests>=2.32.3
